akwlkata
