Metadata-Version: 2.1
Name: akwlkata
Version: 1.0.6
Summary: wlkata robot driver
Home-page: UNKNOWN
Author: Kuture
Author-email: kuture@163.com
License: MIT Licence
Keywords: pip,akwlkata,wlkata,wlkatarobot,kuture,robot
Platform: any
